re_pixel-1.0.1.dist-info/licenses/LICENSE
repixel/__init__.py
repixel/algorithms.py
repixel/cli.py
repixel/compressor.py
repixel/utils.py
re_pixel-1.0.1.dist-info/METADATA
re_pixel-1.0.1.dist-info/WHEEL
re_pixel-1.0.1.dist-info/entry_points.txt
re_pixel-1.0.1.dist-info/top_level.txt
re_pixel-1.0.1.dist-info/RECORD
