Metadata-Version: 2.4
Name: re-pixel
Version: 1.0.1
Summary: A powerful image compression library with multiple algorithms and formats support
Author-email: Rakshith Kalmadi <rakshithkalmadi@gmail.com>
License-Expression: MIT
Project-URL: Homepage, https://github.com/rakshithkalmadi/re-pixel
Project-URL: Bug Tracker, https://github.com/rakshithkalmadi/re-pixel/issues
Project-URL: Source Code, https://github.com/rakshithkalmadi/re-pixel
Keywords: image,compression,optimization,jpeg,png,webp
Classifier: Development Status :: 4 - Beta
Classifier: Intended Audience :: Developers
Classifier: Operating System :: OS Independent
Classifier: Programming Language :: Python :: 3
Classifier: Programming Language :: Python :: 3.7
Classifier: Programming Language :: Python :: 3.8
Classifier: Programming Language :: Python :: 3.9
Classifier: Programming Language :: Python :: 3.10
Classifier: Programming Language :: Python :: 3.11
Classifier: Topic :: Multimedia :: Graphics :: Graphics Conversion
Classifier: Topic :: Software Development :: Libraries :: Python Modules
Requires-Python: >=3.7
License-File: LICENSE
Requires-Dist: Pillow>=9.0.0
Requires-Dist: opencv-python>=4.5.0
Requires-Dist: click>=8.0.0
Requires-Dist: tqdm>=4.60.0
Requires-Dist: numpy>=1.20.0
Provides-Extra: dev
Requires-Dist: pytest>=6.0; extra == "dev"
Requires-Dist: pytest-cov; extra == "dev"
Requires-Dist: black; extra == "dev"
Requires-Dist: flake8; extra == "dev"
Requires-Dist: mypy; extra == "dev"
Requires-Dist: twine; extra == "dev"
Requires-Dist: build; extra == "dev"
Requires-Dist: invoke; extra == "dev"
Dynamic: license-file
